srm_aggregate/__init__.py
srm_aggregate/event_filter.py
srm_aggregate/list_table.py
srm_aggregate/main.py
srm_aggregate/main_window.enaml
srm_aggregate/util.py
srm_aggregate/version.py
srm_aggregate-0.0.1.dist-info/METADATA
srm_aggregate-0.0.1.dist-info/WHEEL
srm_aggregate-0.0.1.dist-info/entry_points.txt
srm_aggregate-0.0.1.dist-info/top_level.txt
srm_aggregate-0.0.1.dist-info/RECORD
