Metadata-Version: 2.1
Name: srm-aggregate
Version: 0.0.1
Summary: Custom code for facilitating SRM analyses
Author-email: "Buran Consulting, LLC" <info@bradburan.com>
Maintainer-email: "Buran Consulting, LLC" <info@bradburan.com>
Requires-Python: >=3.10
Requires-Dist: enaml[qt6-pyside] (>=0.16.1)
Requires-Dist: pandas
Requires-Dist: xlsxwriter
